doorpost_detector/__init__.py
doorpost_detector/api.py
doorpost_detector/pointcloud_processor.py
doorpost_detector/vizualisation.py
doorpost_detector/utils/__init__.py
doorpost_detector/utils/converters.py
doorpost_detector/utils/o3d_arrow.py
doorpost_detector/utils/viz_lvl.py
doorpost_detector-0.1.0.dist-info/METADATA
doorpost_detector-0.1.0.dist-info/WHEEL
doorpost_detector-0.1.0.dist-info/top_level.txt
doorpost_detector-0.1.0.dist-info/RECORD
