Metadata-Version: 2.1
Name: doorpost-detector
Version: 0.1.0
Summary: Detect doorposts from pointclouds
Home-page: https://github.com/h0uter/doorpost_detector
Author: Wouter Meijer
Author-email: 
License: MIT
Platform: UNKNOWN
Classifier: License :: OSI Approved :: MIT License
Classifier: Programming Language :: Python :: 3
Classifier: Programming Language :: Python :: 3.7
Requires-Dist: numpy
Requires-Dist: open3d
Requires-Dist: pyransac3d
Requires-Dist: matplotlib
